{
  "Ok": [
    {
      "id": 1782843,
      "character": {
        "id": 11402,
        "name": "Thellim",
        "screenname": "out-of-equilibrium"
      },
      "character_name": "Thellim",
      "content": "<p>She doesn't particularly suspect that there's a Grimdark Conspiracy out to sabotage everyone else's ability to do science.&nbsp; But only because Thellim has concluded that the Earth's moon is sabotaging <em>fully everyone's </em>ability to do science.</p>\r\n<p>(In Thellim's defense, it is an extremely suspicious moon. &nbsp;It grants magical powers during lunar eclipses. &nbsp;Few dath ilani would <em>not </em>be suspicious that this moon had something to do with the problem.)</p>",
      "created_at": "2022-03-29T01:52:53.170+00:00",
      "icon": {
        "id": 192155,
        "keyword": "smile",
        "url": "https://d1anwqy6ci9o1i.cloudfront.net/users%2F366%2Ficons%2Fwyv1n0155sdrgkb7svtzcp_aimee-garcia-lucifer-3404491.jpg"
      },
      "updated_at": "2022-03-29T01:55:34.793+00:00",
      "user": {
        "id": 366,
        "username": "Iarwain"
      }
    },
    {
      "id": 1782853,
      "character": {
        "id": 13437,
        "name": "Eclipse",
        "screenname": "Earth's-shadow"
      },
      "character_name": "Eclipse",
      "content": "<p>The problem with Bayesianism* is that it's too subjective.</p>\r\n<p>&nbsp;</p>\r\n<p>(*) &nbsp;A four-or-five-syllable Earth term that refers, if anything in their language does, to the forms for reasoning lawfully about probability as spotlighted by coherence theorems; though even among the few Earthlings who've heard of the word, far fewer have heard of coherence theorems.</p>",
      "created_at": "2022-03-29T02:10:15.931+00:00",
      "icon": {
        "id": 248121,
        "keyword": "shadowed earth",
        "url": "https://d1anwqy6ci9o1i.cloudfront.net/users%2F366%2Ficons%2Fzoi28mrzgqc3rb50v1apdm_shadowed+earth.png"
      },
      "updated_at": "2022-03-29T02:10:35.436+00:00",
      "user": {
        "id": 366,
        "username": "Iarwain"
      }
    },
    {
      "id": 1782855,
      "character": {
        "id": 11402,
        "name": "Thellim",
        "screenname": "out-of-equilibrium"
      },
      "character_name": "Thellim",
      "content": "<p>Too subjective.</p>",
      "created_at": "2022-03-29T02:11:20.316+00:00",
      "icon": {
        "id": 193198,
        "keyword": "looking right",
        "url": "https://d1anwqy6ci9o1i.cloudfront.net/users%2F366%2Ficons%2F3oor0ij084j7z9tsp6g1nf_aimee-garcia-lucifer-3404573.jpg"
      },
      "updated_at": "2022-03-29T02:11:20.316+00:00",
      "user": {
        "id": 366,
        "username": "Iarwain"
      }
    },
    {
      "id": 1782856,
      "character": {
        "id": 11402,
        "name": "Thellim",
        "screenname": "out-of-equilibrium"
      },
      "character_name": "Thellim",
      "content": "<p>Too subjective.</p>",
      "created_at": "2022-03-29T02:11:40.558+00:00",
      "icon": {
        "id": 192508,
        "keyword": "looking up",
        "url": "https://d1anwqy6ci9o1i.cloudfront.net/users%2F366%2Ficons%2Fnjn216klk3pyjiirl2qm1m_aimee-garcia-lucifer-3404546.jpg"
      },
      "updated_at": "2022-03-29T02:11:40.558+00:00",
      "user": {
        "id": 366,
        "username": "Iarwain"
      }
    },
    {
      "id": 1782857,
      "character": {
        "id": 11402,
        "name": "Thellim",
        "screenname": "out-of-equilibrium"
      },
      "character_name": "Thellim",
      "content": "<p><em>Too subjective.</em></p>",
      "created_at": "2022-03-29T02:12:17.073+00:00",
      "icon": {
        "id": 192507,
        "keyword": "determined",
        "url": "https://d1anwqy6ci9o1i.cloudfront.net/users%2F366%2Ficons%2Fkupnmepgnv82d1vb18ee3_aimee-garcia-lucifer-3404549.jpg"
      },
      "updated_at": "2022-03-29T02:12:17.073+00:00",
      "user": {
        "id": 366,
        "username": "Iarwain"
      }
    },
    {
      "id": 1782859,
      "character": {
        "id": 11402,
        "name": "Thellim",
        "screenname": "out-of-equilibrium"
      },
      "character_name": "Thellim",
      "content": "<p>Would the Earthling care to explain what is&nbsp;<em>less subjective</em> about <em>any </em>of the deranged pseudo-mathematical constructs used in Earth 'science'?</p>",
      "created_at": "2022-03-29T02:15:22.999+00:00",
      "icon": {
        "id": 192147,
        "keyword": "grimace smile wide eyes",
        "url": "https://d1anwqy6ci9o1i.cloudfront.net/users%2F366%2Ficons%2F76y95ibxd14a2u1so9rkrt_aimee-garcia-lucifer-3404485.jpg"
      },
      "updated_at": "2022-03-29T02:15:22.999+00:00",
      "user": {
        "id": 366,
        "username": "Iarwain"
      }
    },
    {
      "id": 1782861,
      "character": {
        "id": 13437,
        "name": "Eclipse",
        "screenname": "Earth's-shadow"
      },
      "character_name": "Eclipse",
      "content": "<p>Well, for example, let's say you flip a possibly biased coin 10 times.&nbsp; It's an objective fact that if the coin is <em>not</em> biased, the long-run frequency of occasions where 10 coinflips have 9 or more heads, <em>or </em>1 or fewer heads, is 22/1024.&nbsp; So if we adopt the rule 'say the coin is biased if there's at most one head or at most one tail after 10 flips', we're adopting a rule which only rejects the null hypothesis, on occasions where the null hypothesis is in fact true, with 2% frequency in the long run.</p>\r\n<p>This is a fact.&nbsp; It is an objective fact.&nbsp; Right?</p>",
      "created_at": "2022-03-29T02:31:23.779+00:00",
      "icon": {
        "id": 248121,
        "keyword": "shadowed earth",
        "url": "https://d1anwqy6ci9o1i.cloudfront.net/users%2F366%2Ficons%2Fzoi28mrzgqc3rb50v1apdm_shadowed+earth.png"
      },
      "updated_at": "2022-03-29T02:31:23.779+00:00",
      "user": {
        "id": 366,
        "username": "Iarwain"
      }
    },
    {
      "id": 1782862,
      "character": {
        "id": 11402,
        "name": "Thellim",
        "screenname": "out-of-equilibrium"
      },
      "character_name": "Thellim",
      "content": "<p>It's a valid derivation from the stated assumptions, given the laws of probability, yes.&nbsp; If you write a simulation program to flip fair coins ten times, and beep when the number of heads is 0, 1, 9, or 10, the program will beep with 2% probability each time it's run -</p>",
      "created_at": "2022-03-29T02:34:07.043+00:00",
      "icon": {
        "id": 192146,
        "keyword": "looking at you",
        "url": "https://d1anwqy6ci9o1i.cloudfront.net/users%2F366%2Ficons%2F585geu43u2o70pa3bvmswo_aimee-garcia-lucifer-3404504.jpg"
      },
      "updated_at": "2022-03-29T02:34:07.043+00:00",
      "user": {
        "id": 366,
        "username": "Iarwain"
      }
    },
    {
      "id": 1782863,
      "character": {
        "id": 13437,
        "name": "Eclipse",
        "screenname": "Earth's-shadow"
      },
      "character_name": "Eclipse",
      "content": "<p>The more correct way to say it would be that the long-run frequency of occasions where the program beeps will tend towards 22/1024 as a limit.&nbsp; That's an objective statement that is definitely true, where it's more controversial to say that it's meaningful to talk of there being a 2% probability of the program beeping on the&nbsp;<em>next</em> occasion it runs.&nbsp; That either happens or it doesn't, so in what sense could the number 2% be true about it?</p>",
      "created_at": "2022-03-29T02:35:40.244+00:00",
      "icon": {
        "id": 248121,
        "keyword": "shadowed earth",
        "url": "https://d1anwqy6ci9o1i.cloudfront.net/users%2F366%2Ficons%2Fzoi28mrzgqc3rb50v1apdm_shadowed+earth.png"
      },
      "updated_at": "2022-03-29T02:35:40.244+00:00",
      "user": {
        "id": 366,
        "username": "Iarwain"
      }
    },
    {
      "id": 1782869,
      "character": {
        "id": 11402,
        "name": "Thellim",
        "screenname": "out-of-equilibrium"
      },
      "character_name": "Thellim",
      "content": "<p>The way that truth-functionals on propositions generalize to truth-functionals on probability assignments, is that you say 2% and then you lose, like, 5 or 6 bits or so, if you're wrong, and lose a small fraction of a bit, if you're right.</p>\r\n<p>It's slightly more complicated than mentally comparing the proposition 'snow is white' to a handful of snow and thinking that it's meaningful to talk of this proposition being 'true'.&nbsp; Very slightly.&nbsp; If you can do one you're probably smart enough to do the other, really.</p>\r\n<p>If one denies that there is such a thing as a 2% probability that the program beeps on the&nbsp;<em>next occasion,</em> why couldn't you just imagine that you repeatedly run the program and it never beeps on any occasion forever?&nbsp; That's a&nbsp;<em>possible</em> thing that happens when you keep flipping coins.&nbsp; It's&nbsp;<em>improbable</em> but it's&nbsp;<em>possible.</em></p>",
      "created_at": "2022-03-29T02:41:46.474+00:00",
      "icon": {
        "id": 192157,
        "keyword": "gentle smile",
        "url": "https://d1anwqy6ci9o1i.cloudfront.net/users%2F366%2Ficons%2Fnq69wmplnxqx9h6xte9h9l_aimee-garcia-lucifer-3404483.jpg"
      },
      "updated_at": "2022-03-30T19:31:48.264+00:00",
      "user": {
        "id": 366,
        "username": "Iarwain"
      }
    },
    {
      "id": 1782871,
      "character": {
        "id": 13437,
        "name": "Eclipse",
        "screenname": "Earth's-shadow"
      },
      "character_name": "Eclipse",
      "content": "<p>The probability tends to zero as a limit.</p>",
      "created_at": "2022-03-29T02:42:10.515+00:00",
      "icon": {
        "id": 248121,
        "keyword": "shadowed earth",
        "url": "https://d1anwqy6ci9o1i.cloudfront.net/users%2F366%2Ficons%2Fzoi28mrzgqc3rb50v1apdm_shadowed+earth.png"
      },
      "updated_at": "2022-03-29T02:42:10.515+00:00",
      "user": {
        "id": 366,
        "username": "Iarwain"
      }
    },
    {
      "id": 1782874,
      "character": {
        "id": 11402,
        "name": "Thellim",
        "screenname": "out-of-equilibrium"
      },
      "character_name": "Thellim",
      "content": "<p>So this quantity that is supposedly meaningless tends to zero as a limit, which is, itself, apparently a very meaningful thing to say?&nbsp; Yes, that sounds like a very consistent philosophy to have about the world.</p>\r\n<p>After any finite number of steps, it will still, apparently, on his view, be <em>objectively meaningless</em> to talk about the probability that a program beeps at least once.</p>\r\n<p>Therefore, the meta-proposition 'is it meaningful to talk about the probability of this program beeping at least once' will tend towards 'false' as a limit, on his philosophy -</p>",
      "created_at": "2022-03-29T02:46:27.069+00:00",
      "icon": {
        "id": 192800,
        "keyword": "looking aside",
        "url": "https://d1anwqy6ci9o1i.cloudfront.net/users%2F366%2Ficons%2Ft83vvj4juredsuhfzfd3ka_aimee-garcia-lucifer-3404585.jpg"
      },
      "updated_at": "2022-03-29T02:46:27.069+00:00",
      "user": {
        "id": 366,
        "username": "Iarwain"
      }
    },
    {
      "id": 1782876,
      "character": {
        "id": 13437,
        "name": "Eclipse",
        "screenname": "Earth's-shadow"
      },
      "character_name": "Eclipse",
      "content": "<p>Okay, look, it's not like that, it's more like - that the long-run frequency of programs beeping is 22/1024, is a valid consequence of the premise that the coin is fair.&nbsp; That's just a true statement about the long-run frequency, with no probabilities involved.&nbsp; It's how you reduce claims about probability to simpler claims that don't have probabilities in them, by looking at something which actually has a 22/1024 proportion of whatever.</p>",
      "created_at": "2022-03-29T02:47:33.571+00:00",
      "icon": {
        "id": 248121,
        "keyword": "shadowed earth",
        "url": "https://d1anwqy6ci9o1i.cloudfront.net/users%2F366%2Ficons%2Fzoi28mrzgqc3rb50v1apdm_shadowed+earth.png"
      },
      "updated_at": "2022-03-30T19:33:32.203+00:00",
      "user": {
        "id": 366,
        "username": "Iarwain"
      }
    },
    {
      "id": 1782877,
      "character": {
        "id": 11402,
        "name": "Thellim",
        "screenname": "out-of-equilibrium"
      },
      "character_name": "Thellim",
      "content": "<p>This true statement about the hypothetical is derived from reasoning steps that go through probabilities.&nbsp; After you've flipped the coin fifty times, for five runs of the program, there's thirty-two possible sequences of beeping and not beeping.&nbsp; Extending these sequence lengths out towards an infinite limit, the sequences more than delta away from 22/1024 beep frequencies will tend to go under epsilon fraction of the total probability.&nbsp; This is the only meaningful statement that can be made here about a 'long-run frequency', unless he wants to start taking direct ratios of countable infinities.&nbsp; When the sequences are actually infinite, we can no longer directly speak of things having 22/1024 ratios inside them.</p>\r\n<p>This limit is being obtained by considering<em> the probability of the possible finite beep sequences,</em> which is supposedly 'subjective' and forbidden.</p>",
      "created_at": "2022-03-29T02:53:31.138+00:00",
      "icon": {
        "id": 192146,
        "keyword": "looking at you",
        "url": "https://d1anwqy6ci9o1i.cloudfront.net/users%2F366%2Ficons%2F585geu43u2o70pa3bvmswo_aimee-garcia-lucifer-3404504.jpg"
      },
      "updated_at": "2022-04-12T22:15:16.580+00:00",
      "user": {
        "id": 366,
        "username": "Iarwain"
      }
    },
    {
      "id": 1782878,
      "character": {
        "id": 13437,
        "name": "Eclipse",
        "screenname": "Earth's-shadow"
      },
      "character_name": "Eclipse",
      "content": "<p>Right, but the&nbsp;<em>final </em>conclusion is a certain one, which makes it objective, unlike the statement that a fair coin has a 2% probability of yielding less than 2 or more than 8 heads on the&nbsp;<em>next occasion,</em> when either it does or it doesn't.</p>",
      "created_at": "2022-03-29T02:54:29.268+00:00",
      "icon": {
        "id": 248121,
        "keyword": "shadowed earth",
        "url": "https://d1anwqy6ci9o1i.cloudfront.net/users%2F366%2Ficons%2Fzoi28mrzgqc3rb50v1apdm_shadowed+earth.png"
      },
      "updated_at": "2022-03-29T02:54:29.268+00:00",
      "user": {
        "id": 366,
        "username": "Iarwain"
      }
    },
    {
      "id": 1782879,
      "character": {
        "id": 11402,
        "name": "Thellim",
        "screenname": "out-of-equilibrium"
      },
      "character_name": "Thellim",
      "content": "<p>Thellim might, under other circumstances, try to ask if his rules of metaphysics permit one to derive an 'objective' truth via a series of reasoning steps whose intermediates are 'not objective'.</p>\r\n<p>She reminds herself that this person has in fact been driven crazy by the moon and she is not <em>actually</em> going to be able to argue him out of anything.&nbsp; The main thing Thellim should do is note down that a manifestation of the compulsion appears to be a feeling that some complicated derivations of the probability axioms are 'objective', and the simpler steps of reasoning leading up to that conclusion are 'subjective', and that then the person refuses to accept the 'subjective' parts even though in principle they're how the 'objective' truth is derived.&nbsp; They <em>skip over </em>the derivation, and feel like they can just go from the supposed premise to the 'objective' conclusion about long-runs, without any 'subjective' statements about short runs along the way.</p>\r\n<p>Presumably this is what it feels like from the inside, after the moon has excluded from your mind all the simple and obvious ways to do science, and you've had to resort to fantastically complicated methods outside the boundary of what the moon is excluding.&nbsp; The word 'subjective' is really just referring to whatever the moon prevents them from believing.&nbsp; If you point out that their 'objective' statements are derived from 'subjective' intermediates in principle, they'll just jump all the way to the conclusion in what they claim to be one jump, maybe...?</p>\r\n<p>Let's try a different tack.</p>",
      "created_at": "2022-03-29T03:04:01.589+00:00",
      "icon": {
        "id": 192142,
        "keyword": "skeptical",
        "url": "https://d1anwqy6ci9o1i.cloudfront.net/users%2F366%2Ficons%2Ftzvq7j8m93j7i3g7pxu5_aimee-garcia-lucifer-3404543.jpg"
      },
      "updated_at": "2022-03-29T03:04:01.589+00:00",
      "user": {
        "id": 366,
        "username": "Iarwain"
      }
    },
    {
      "id": 1782889,
      "character": {
        "id": 11402,
        "name": "Thellim",
        "screenname": "out-of-equilibrium"
      },
      "character_name": "Thellim",
      "content": "<p>Well, Thellim does in fact concede that the long-run frequency of occasions where this hypothetical fair-coin-flips-10-times program beeps, will tend towards 22/1024 as a limit.&nbsp; She just thinks that it's not particularly plausible to have an epistemology of probability where you can say that, and exclude the idea that the next run of the program has a 2% probability of beeping.&nbsp; In both cases you're just talking about a logical consequence of an uncertainty-containing model where the coin has an independent 50% probability of coming up heads each time, that your mind imagines being compared to reality using a logloss correspondence, and which you can actually score once you make the actual observations.</p>\r\n<p>That this is not something you can derive from&nbsp;<em>the long-run frequency of the coin yielding heads being 50%,</em> as opposed to the statement that&nbsp;<em>the coin has independently a 50% chance of showing heads on each occasion,</em> is readily shown by considering the case of a coin that perfectly alternates heads and tails inside every run.&nbsp; This coin has a long-run frequency of 50% heads, and also, the head-counting program run over it will never beep -</p>",
      "created_at": "2022-03-29T03:12:59.077+00:00",
      "icon": {
        "id": 193197,
        "keyword": "looking right",
        "url": "https://d1anwqy6ci9o1i.cloudfront.net/users%2F366%2Ficons%2Fixyaja1qroru6ah7lxgw_aimee-garcia-lucifer-3404575.jpg"
      },
      "updated_at": "2022-03-31T17:11:48.411+00:00",
      "user": {
        "id": 366,
        "username": "Iarwain"
      }
    },
    {
      "id": 1782890,
      "character": {
        "id": 13437,
        "name": "Eclipse",
        "screenname": "Earth's-shadow"
      },
      "character_name": "Eclipse",
      "content": "<p>They're really getting a bit outside his area of expertise here, he's a scientist, not an epistemologist.&nbsp; But presumably the definition of a long-run frequency also includes, for example, the idea that subsequences of two coinflips, HH, HT, TH, and TT, all have 25% frequency, within the long run.</p>",
      "created_at": "2022-03-29T03:14:07.987+00:00",
      "icon": {
        "id": 248121,
        "keyword": "shadowed earth",
        "url": "https://d1anwqy6ci9o1i.cloudfront.net/users%2F366%2Ficons%2Fzoi28mrzgqc3rb50v1apdm_shadowed+earth.png"
      },
      "updated_at": "2022-03-29T03:17:04.998+00:00",
      "user": {
        "id": 366,
        "username": "Iarwain"
      }
    },
    {
      "id": 1782891,
      "character": {
        "id": 11402,
        "name": "Thellim",
        "screenname": "out-of-equilibrium"
      },
      "character_name": "Thellim",
      "content": "<p>This is either an infinite set of independent postulates none of which can be derived from each other or any simpler postulates, or they are the collection of simple deductive consequences of a model in which the coin has an independent 50% probability of coming up heads each time.</p>\r\n<p><br />(Can he not&nbsp;<em>see</em> where his axioms are coming from, the excluded space inside his own mind... he can see the <em>consequences</em> of excluded beliefs, so they're probably still <em>in</em> there in some sense... it's just that when he thinks about them consciously, the moon forces him to label those thoughts as meaningless and 'subjective' and therefore bad, but that doesn't mean he can't intuit the consequences...)</p>",
      "created_at": "2022-03-29T03:16:22.551+00:00",
      "icon": {
        "id": 192154,
        "keyword": "serious 1",
        "url": "https://d1anwqy6ci9o1i.cloudfront.net/users%2F366%2Ficons%2Fmeuvbswa88mpefrsnr0roo_aimee-garcia-lucifer-3404465.jpg"
      },
      "updated_at": "2022-03-29T05:25:51.042+00:00",
      "user": {
        "id": 366,
        "username": "Iarwain"
      }
    },
    {
      "id": 1782892,
      "character": {
        "id": 13437,
        "name": "Eclipse",
        "screenname": "Earth's-shadow"
      },
      "character_name": "Eclipse",
      "content": "<p>Look, he's not actually a philosophy-of-science guy.</p>",
      "created_at": "2022-03-29T03:16:48.774+00:00",
      "icon": {
        "id": 248121,
        "keyword": "shadowed earth",
        "url": "https://d1anwqy6ci9o1i.cloudfront.net/users%2F366%2Ficons%2Fzoi28mrzgqc3rb50v1apdm_shadowed+earth.png"
      },
      "updated_at": "2022-03-29T03:16:48.774+00:00",
      "user": {
        "id": 366,
        "username": "Iarwain"
      }
    },
    {
      "id": 1782897,
      "character": {
        "id": 11402,
        "name": "Thellim",
        "screenname": "out-of-equilibrium"
      },
      "character_name": "Thellim",
      "content": "<p>Being one of the smartest people on the planet, and the literally actually sanest person on it, is something that Thellim is still having trouble coming to grips with.&nbsp; She isn't even a professional in any particular subspecialty of science, like report-writing or experiment-performance or experiment-analysis.&nbsp; She just knows what&nbsp;<em>eight-year-olds</em> are supposed to know about science so they can read <em>newspaper stories </em>about it.</p>\r\n<p>Which makes her&nbsp;<em>all that this Earth has in the way of sane scientific methodology literally at all,</em> and if she's going to do anything with that, she may need to get it done before the next lunar eclipse, which is now only three months away.</p>",
      "created_at": "2022-03-29T03:28:11.858+00:00",
      "icon": {
        "id": 192508,
        "keyword": "looking up",
        "url": "https://d1anwqy6ci9o1i.cloudfront.net/users%2F366%2Ficons%2Fnjn216klk3pyjiirl2qm1m_aimee-garcia-lucifer-3404546.jpg"
      },
      "updated_at": "2022-03-29T05:26:16.528+00:00",
      "user": {
        "id": 366,
        "username": "Iarwain"
      }
    },
    {
      "id": 1782899,
      "character": {
        "id": 11402,
        "name": "Thellim",
        "screenname": "out-of-equilibrium"
      },
      "character_name": "Thellim",
      "content": "<p>Can she possibly sell him on the idea that it would maybe be a better idea for experimental reports to report some&nbsp;<em>different</em> consequences of the probability axioms, even if those consequences are 'subjective'?&nbsp; She realizes it probably feels very bad to talk about a consequence of the probability axioms that feels 'subjective'.&nbsp; But, if it were super important, like maybe there were a lot of money at stake or something, people could talk about <em>other </em>deductive consequences of probability models that could be matched up against experimental realities?&nbsp; Even though they seem to be 'subjective' and that's very bad?</p>",
      "created_at": "2022-03-29T03:30:39.375+00:00",
      "icon": {
        "id": 193198,
        "keyword": "looking right",
        "url": "https://d1anwqy6ci9o1i.cloudfront.net/users%2F366%2Ficons%2F3oor0ij084j7z9tsp6g1nf_aimee-garcia-lucifer-3404573.jpg"
      },
      "updated_at": "2022-03-29T03:31:37.906+00:00",
      "user": {
        "id": 366,
        "username": "Iarwain"
      }
    },
    {
      "id": 1782902,
      "character": {
        "id": 13437,
        "name": "Eclipse",
        "screenname": "Earth's-shadow"
      },
      "character_name": "Eclipse",
      "content": "<p>&nbsp;</p>\r\n<p>Like what?</p>",
      "created_at": "2022-03-29T03:32:42.074+00:00",
      "icon": {
        "id": 248121,
        "keyword": "shadowed earth",
        "url": "https://d1anwqy6ci9o1i.cloudfront.net/users%2F366%2Ficons%2Fzoi28mrzgqc3rb50v1apdm_shadowed+earth.png"
      },
      "updated_at": "2022-03-29T03:32:42.074+00:00",
      "user": {
        "id": 366,
        "username": "Iarwain"
      }
    },
    {
      "id": 1782904,
      "character": {
        "id": 11402,
        "name": "Thellim",
        "screenname": "out-of-equilibrium"
      },
      "character_name": "Thellim",
      "content": "<p>Likelihoods.&nbsp; Likelihood functions.&nbsp; Likelihood ratios.</p>\r\n<p>If you flip a coin and see eight heads and two tails, you report, first of all, the actual exact sequence you observed including the ordering, and as summary, that the likelihood of this data given any underlying independent propensity <em>p</em> for the coin to yield heads, is equal to (<em>p</em>)^8 * (1-<em>p</em>)^2.</p>\r\n<p>For 80% propensity it'd be... 2^26/10^10, and for 20% propensity it'd be 2^14/10^10, for example.</p>\r\n<p>This is an axiomatic, deductive, fully valid and determined consequence of that hypothesis about the coin.</p>",
      "created_at": "2022-03-29T03:37:42.595+00:00",
      "icon": {
        "id": 192152,
        "keyword": "questioning",
        "url": "https://d1anwqy6ci9o1i.cloudfront.net/users%2F366%2Ficons%2F05p2l4c50kvrwcd0gtqk5p_aimee-garcia-lucifer-3404496.jpg"
      },
      "updated_at": "2022-03-29T08:57:01.307+00:00",
      "user": {
        "id": 366,
        "username": "Iarwain"
      }
    },
    {
      "id": 1782905,
      "character": {
        "id": 13437,
        "name": "Eclipse",
        "screenname": "Earth's-shadow"
      },
      "character_name": "Eclipse",
      "content": "<p>He knows what 'likelihoods' are, which makes him very smart and well-educated for an Earthling scientist!</p>\r\n<p>He's heard that they have to be combined with 'priors' in order to make any use of them, though.&nbsp; Priors are very subjective.</p>",
      "created_at": "2022-03-29T03:39:07.191+00:00",
      "icon": {
        "id": 248121,
        "keyword": "shadowed earth",
        "url": "https://d1anwqy6ci9o1i.cloudfront.net/users%2F366%2Ficons%2Fzoi28mrzgqc3rb50v1apdm_shadowed+earth.png"
      },
      "updated_at": "2022-03-29T03:39:07.191+00:00",
      "user": {
        "id": 366,
        "username": "Iarwain"
      }
    },
    {
      "id": 1782911,
      "character": {
        "id": 11402,
        "name": "Thellim",
        "screenname": "out-of-equilibrium"
      },
      "character_name": "Thellim",
      "content": "<p>Okay, but... how much money would he need to be paid to report likelihood functions anyways, despite their being associated with priors, which are 'subjective'?&nbsp; Is it possibly just a hundred bucks, if he focuses hard on the feeling, and considers how, even though 'subjectivity' seems like a very bad thing, there isn't any actual concrete terrible bad thing that happens to you?&nbsp; Especially if you <em>just</em> report likelihood functions, and <em>don't</em> talk about any priors or posteriors on the real-world facts (as opposed to internal model variables being integrated out).&nbsp; As is standard practice anyways, because other people might know something you don't, and because your report isn't a realtime-updated prediction market -</p>",
      "created_at": "2022-03-29T03:43:44.487+00:00",
      "icon": {
        "id": 193237,
        "keyword": "zoomed smile",
        "url": "https://d1anwqy6ci9o1i.cloudfront.net/users%2F366%2Ficons%2Fmna1nt90ofbky72fh7fqpf_aimee-garcia-lucifer-3404490.jpg"
      },
      "updated_at": "2022-03-29T05:28:47.685+00:00",
      "user": {
        "id": 366,
        "username": "Iarwain"
      }
    },
    {
      "id": 1782916,
      "character": {
        "id": 13437,
        "name": "Eclipse",
        "screenname": "Earth's-shadow"
      },
      "character_name": "Eclipse",
      "content": "<p>Well, no, the thing he'd worry about is that if you report on the data having whatever-it-was likelihood, given the coin's propensity to heads of 20%, somebody will decide that, even though this likelihood was pretty low, the coin still has a trillion-to-one prior probability of having a 20% propensity to heads!</p>\r\n<p>Wouldn't this make the scientific process open to obvious abuses?&nbsp; What then?</p>",
      "created_at": "2022-03-29T03:46:31.454+00:00",
      "icon": {
        "id": 248121,
        "keyword": "shadowed earth",
        "url": "https://d1anwqy6ci9o1i.cloudfront.net/users%2F366%2Ficons%2Fzoi28mrzgqc3rb50v1apdm_shadowed+earth.png"
      },
      "updated_at": "2022-03-29T03:46:31.454+00:00",
      "user": {
        "id": 366,
        "username": "Iarwain"
      }
    },
    {
      "id": 1782918,
      "character": {
        "id": 11402,
        "name": "Thellim",
        "screenname": "out-of-equilibrium"
      },
      "character_name": "Thellim",
      "content": "<p>Ideally?&nbsp; In a saner world?&nbsp; Whoever says that can lose a ton of money on prediction markets about what the next experiment will show on the same coin!</p>",
      "created_at": "2022-03-29T03:48:11.939+00:00",
      "icon": {
        "id": 192147,
        "keyword": "grimace smile wide eyes",
        "url": "https://d1anwqy6ci9o1i.cloudfront.net/users%2F366%2Ficons%2F76y95ibxd14a2u1so9rkrt_aimee-garcia-lucifer-3404485.jpg"
      },
      "updated_at": "2022-03-29T05:52:51.475+00:00",
      "user": {
        "id": 366,
        "username": "Iarwain"
      }
    },
    {
      "id": 1782919,
      "character": {
        "id": 13437,
        "name": "Eclipse",
        "screenname": "Earth's-shadow"
      },
      "character_name": "Eclipse",
      "content": "<p>Aren't prediction markets about that sort of thing illegal because of gambling laws?</p>",
      "created_at": "2022-03-29T03:48:29.018+00:00",
      "icon": {
        "id": 248121,
        "keyword": "shadowed earth",
        "url": "https://d1anwqy6ci9o1i.cloudfront.net/users%2F366%2Ficons%2Fzoi28mrzgqc3rb50v1apdm_shadowed+earth.png"
      },
      "updated_at": "2022-03-29T03:48:29.018+00:00",
      "user": {
        "id": 366,
        "username": "Iarwain"
      }
    },
    {
      "id": 1782921,
      "character": {
        "id": 11402,
        "name": "Thellim",
        "screenname": "out-of-equilibrium"
      },
      "character_name": "Thellim",
      "content": "<p>Thellim is aware.&nbsp; Sometimes she likes to pretend she's somewhere else where that isn't true.</p>",
      "created_at": "2022-03-29T03:49:07.322+00:00",
      "icon": {
        "id": 193422,
        "keyword": "go right",
        "url": "https://d1anwqy6ci9o1i.cloudfront.net/users%2F366%2Ficons%2F0rofamndbsli7w7ltnlqy9h_aimee-garcia-lucifer-3404516.jpg"
      },
      "updated_at": "2022-03-29T03:49:07.322+00:00",
      "user": {
        "id": 366,
        "username": "Iarwain"
      }
    },
    {
      "id": 1782922,
      "character": {
        "id": 13437,
        "name": "Eclipse",
        "screenname": "Earth's-shadow"
      },
      "character_name": "Eclipse",
      "content": "<p>To be clear, he's not especially a supporter of those laws himself -</p>",
      "created_at": "2022-03-29T03:49:32.508+00:00",
      "icon": {
        "id": 248121,
        "keyword": "shadowed earth",
        "url": "https://d1anwqy6ci9o1i.cloudfront.net/users%2F366%2Ficons%2Fzoi28mrzgqc3rb50v1apdm_shadowed+earth.png"
      },
      "updated_at": "2022-03-29T03:49:32.508+00:00",
      "user": {
        "id": 366,
        "username": "Iarwain"
      }
    },
    {
      "id": 1782925,
      "character": {
        "id": 11402,
        "name": "Thellim",
        "screenname": "out-of-equilibrium"
      },
      "character_name": "Thellim",
      "content": "<p>Yes.&nbsp; Thank you for the sentiment.</p>\r\n<p>As it happens, a sane scientific process says that putting a prior probability like that, on any particular effect-size, or reporting a posterior after seeing the data, isn't supposed to be the job of experimentalists in the first place. So maybe this is a place where that whole horror of the 'subjective' could work in their favor.</p>\r\n<p>And has he noticed that there's... kind of a&nbsp;<em>lot</em> of end-user-manipulable free variables inside the 'frequentist' procedures that have been constructed in incredibly elaborate ways so as to avoid all mention of likelihoods?</p>",
      "created_at": "2022-03-29T03:58:18.442+00:00",
      "icon": {
        "id": 192154,
        "keyword": "serious 1",
        "url": "https://d1anwqy6ci9o1i.cloudfront.net/users%2F366%2Ficons%2Fmeuvbswa88mpefrsnr0roo_aimee-garcia-lucifer-3404465.jpg"
      },
      "updated_at": "2022-03-29T08:55:35.332+00:00",
      "user": {
        "id": 366,
        "username": "Iarwain"
      }
    },
    {
      "id": 1782927,
      "character": {
        "id": 13437,
        "name": "Eclipse",
        "screenname": "Earth's-shadow"
      },
      "character_name": "Eclipse",
      "content": "<p>&nbsp;</p>\r\n<p>...is she talking about p-hacking?</p>",
      "created_at": "2022-03-29T03:58:32.038+00:00",
      "icon": {
        "id": 248121,
        "keyword": "shadowed earth",
        "url": "https://d1anwqy6ci9o1i.cloudfront.net/users%2F366%2Ficons%2Fzoi28mrzgqc3rb50v1apdm_shadowed+earth.png"
      },
      "updated_at": "2022-03-29T10:47:00.743+00:00",
      "user": {
        "id": 366,
        "username": "Iarwain"
      }
    },
    {
      "id": 1782929,
      "character": {
        "id": 11402,
        "name": "Thellim",
        "screenname": "out-of-equilibrium"
      },
      "character_name": "Thellim",
      "content": "<p>She's talking about how, if you flip a coin and get the sequence HHHHHT, then this is 'statistically significant' <em>if </em>you got the sequence by following the rule 'Flip until you get the first tail and then stop', in which case the sequence is only six coinflips or longer on 1/32 of occasions, p &lt; 0.05.</p>\r\n<p>And 'fails' to achieve statistical significance if you got exactly the same exact observations by following the rule 'Flip the coin six times and count the tails', in which case there's 7/64 ways to get one or fewer tails, p=11%, n.s.</p>",
      "created_at": "2022-03-29T04:01:48.465+00:00",
      "icon": {
        "id": 193198,
        "keyword": "looking right",
        "url": "https://d1anwqy6ci9o1i.cloudfront.net/users%2F366%2Ficons%2F3oor0ij084j7z9tsp6g1nf_aimee-garcia-lucifer-3404573.jpg"
      },
      "updated_at": "2022-03-29T05:53:25.919+00:00",
      "user": {
        "id": 366,
        "username": "Iarwain"
      }
    },
    {
      "id": 1782991,
      "character": {
        "id": 13437,
        "name": "Eclipse",
        "screenname": "Earth's-shadow"
      },
      "character_name": "Eclipse",
      "content": "<p>Well, no reputable journal would accept the first analysis - it's not the way somebody would normally compute the p-values after collecting the data on six coinflips.&nbsp; Which isn't really very much in the way of coinflips anyways -</p>",
      "created_at": "2022-03-29T05:54:17.667+00:00",
      "icon": {
        "id": 248121,
        "keyword": "shadowed earth",
        "url": "https://d1anwqy6ci9o1i.cloudfront.net/users%2F366%2Ficons%2Fzoi28mrzgqc3rb50v1apdm_shadowed+earth.png"
      },
      "updated_at": "2022-03-29T05:54:17.667+00:00",
      "user": {
        "id": 366,
        "username": "Iarwain"
      }
    },
    {
      "id": 1782994,
      "character": {
        "id": 11402,
        "name": "Thellim",
        "screenname": "out-of-equilibrium"
      },
      "character_name": "Thellim",
      "content": "<p>Or take 95% confidence intervals.&nbsp; One way to get a 95% confidence interval is... whatever the traditional method is, Thellim tried to read it several times but her eyes started to bleed and black tentacles started squirming out from under nearby doors, but it involved taking the average of all the measurements so far, and picking a data-dependent constant <em>c</em> to add and subtract to the mean, to get an interval (mean - <em>c</em>, mean + <em>c</em>) such that following this procedure would, 95% of the time, in the long run, give you a confidence interval that contained the true population average value of the parameter, if you were sampling randomly from that population.</p>\r\n<p>There's also, obviously, going to be a way to pick a constant&nbsp;<em>d</em> where you report the interval (mean - <em>d</em>, mean + 2<em>d</em>) via some method for picking&nbsp;<em>d</em> such that&nbsp;<em>this&nbsp;</em>method will 95% of the time, in the long run, produce an interval containing the true population mean.</p>\r\n<p>Yet another way to get a 95% confidence interval is to, like, construct a 99% confidence interval the traditional way, and then with 4/99 probability, report the interval (purple, blagoobah).&nbsp; It doesn't matter that blagoobah isn't a word.&nbsp; The interval will still contain the true average 95% of the time, in the long run, if the method is separately repeated infinitely many times.</p>",
      "created_at": "2022-03-29T06:01:33.711+00:00",
      "icon": {
        "id": 193235,
        "keyword": "look up right",
        "url": "https://d1anwqy6ci9o1i.cloudfront.net/users%2F366%2Ficons%2Fslscuc9718tg1ebfjfgr_aimee-garcia-lucifer-3404509.jpg"
      },
      "updated_at": "2022-03-29T09:21:51.788+00:00",
      "user": {
        "id": 366,
        "username": "Iarwain"
      }
    },
    {
      "id": 1782995,
      "character": {
        "id": 13437,
        "name": "Eclipse",
        "screenname": "Earth's-shadow"
      },
      "character_name": "Eclipse",
      "content": "<p>He agrees that the second and third methods are worse ways to get 95% confidence intervals than the first method; they'll produce wider intervals with no gain in correctness.</p>",
      "created_at": "2022-03-29T06:02:15.983+00:00",
      "icon": {
        "id": 248121,
        "keyword": "shadowed earth",
        "url": "https://d1anwqy6ci9o1i.cloudfront.net/users%2F366%2Ficons%2Fzoi28mrzgqc3rb50v1apdm_shadowed+earth.png"
      },
      "updated_at": "2022-03-29T06:02:15.983+00:00",
      "user": {
        "id": 366,
        "username": "Iarwain"
      }
    },
    {
      "id": 1782997,
      "character": {
        "id": 11402,
        "name": "Thellim",
        "screenname": "out-of-equilibrium"
      },
      "character_name": "Thellim",
      "content": "<p>What she's trying to get at here is that all the 'p-values' and 'confidence intervals' are&nbsp;<em>much more manipulable </em>than likelihood functions as a summary of the data!</p>\r\n<p>P-values contain free parameters for which class of other possible results you decide to lump in with the exact data that you saw.&nbsp; If you say that the result HHHHHT is part of a class of results that includes {THHHHH, HTHHHH, HHTHHHH, HHHTHH, HHHHTH, HHHHHT, HHHHHH}, then there's 7 lumped-in results like that with total probability 7/64, so you say 'not significant'.&nbsp; If instead you say that HHHHHT is part of a class of results that includes {HHHHHT, HHHHHHT, HHHHHHHT...} then there's infinity lumped-in results like that with total probability 1/32, so you say 'significant'.</p>\r\n<p>Similarly with 'confidence intervals', and all the different ways you could fiddle interval construction, and still have it be a valid deduction that the method would with 95% probability - pardon her, would with 95% frequency in the long run - produce an interval containing the true average measurement.</p>\r\n<p>Likelihood functions don't have free parameters like that!&nbsp; You don't take the actual results you saw and lump them in with other results you didn't see and calculate their summed probability!&nbsp; You don't apply 'methods' to things to draw weird intervals around them!&nbsp; You just use <em>the actual data that you saw!</em>&nbsp; For any <em>sufficiently characterized </em><em>way the world can be,</em> any hypothesis of a sort that experimenters ought to summarize statistics about, there's just some <em>valid deduction</em> about how likely that world was to produce the exact data observed.</p>",
      "created_at": "2022-03-29T06:10:34.777+00:00",
      "icon": {
        "id": 192161,
        "keyword": "incredulous",
        "url": "https://d1anwqy6ci9o1i.cloudfront.net/users%2F366%2Ficons%2F2bzk5g6xzj9l7p0pgbib0p_aimee-garcia-lucifer-3404591.jpg"
      },
      "updated_at": "2022-03-29T09:23:28.979+00:00",
      "user": {
        "id": 366,
        "username": "Iarwain"
      }
    },
    {
      "id": 1783000,
      "character": {
        "id": 13437,
        "name": "Eclipse",
        "screenname": "Earth's-shadow"
      },
      "character_name": "Eclipse",
      "content": "<p>You can't fiddle with the numbers if you're honest, is the idea in science.&nbsp; Science does presume that scientists were honest in reporting which rules they followed to do their experiments; it does assume that somebody who flips a coin six times, gets HHHHHT, and stops, will honestly say that 'they decided to flip the coin six times and then stop' and not lie and say 'I decided in advance that I'd flip the coin until I got tails and then stop'.</p>\r\n<p>So long as nobody lies, though, the free parameters can't be used to <em>cheat</em> - you can't have some clever way of picking the method that lets you get p &lt; 0.05, with probability greater than 5%, when the null hypothesis is actually true.</p>\r\n<p>Science does presume honesty; but absent that presumption, people could just lie about the data anyways, no matter what stats you used.</p>",
      "created_at": "2022-03-29T06:18:20.739+00:00",
      "icon": {
        "id": 248121,
        "keyword": "shadowed earth",
        "url": "https://d1anwqy6ci9o1i.cloudfront.net/users%2F366%2Ficons%2Fzoi28mrzgqc3rb50v1apdm_shadowed+earth.png"
      },
      "updated_at": "2022-03-29T06:25:51.736+00:00",
      "user": {
        "id": 366,
        "username": "Iarwain"
      }
    },
    {
      "id": 1783003,
      "character": {
        "id": 11402,
        "name": "Thellim",
        "screenname": "out-of-equilibrium"
      },
      "character_name": "Thellim",
      "content": "<p>When you flip a coin and get HHHHHT, the meaning of that result&nbsp;<em>should not depend on the experimenter's state of mind</em> unless the experimenter's state of mind&nbsp;<em>is able to affect the coin.</em>&nbsp; What tells you about reality, is what is entangled with reality; the coinflips entangled with the coin; if the experimenter is not telekinetic then <em>who cares what they were thinking.</em></p>\r\n<p>Once you have characterized the world, the likelihood of the data, given that world, doesn't change with what the experimenter is thinking, unless the model says that the experimenter's thoughts are able to affect reality.</p>\r\n<p>And let's be frank here, if Earthlings are not entirely immune to temptation in the face of terrible incentives and no prediction markets and not very much replication, people might be&nbsp;<em>quantitatively more tempted</em> to fudge their&nbsp;<em>unobservable private intentions while conducting their experiment</em> than to fudge the&nbsp;<em>hard objective facts of what was observed</em> that somebody would be&nbsp;<em>more likely to catch them lying about.</em><br /><br /></p>\r\n<p>(Thellim would ask how an epistemology with experimenter's-unobservable-private-intentions-dependent interpretation of the evidence is <em>not </em>'subjective', but she has worked out by this point that 'subjective' actually means 'the moon makes me feel like I hate this' and doesn't really relate to the ordinary English meaning of the word.)</p>",
      "created_at": "2022-03-29T06:22:40.087+00:00",
      "icon": {
        "id": 192157,
        "keyword": "gentle smile",
        "url": "https://d1anwqy6ci9o1i.cloudfront.net/users%2F366%2Ficons%2Fnq69wmplnxqx9h6xte9h9l_aimee-garcia-lucifer-3404483.jpg"
      },
      "updated_at": "2022-03-29T09:24:24.994+00:00",
      "user": {
        "id": 366,
        "username": "Iarwain"
      }
    },
    {
      "id": 1783009,
      "character": {
        "id": 13437,
        "name": "Eclipse",
        "screenname": "Earth's-shadow"
      },
      "character_name": "Eclipse",
      "content": "<p>Well, that's why there's very standard methods for computing the p-values, which, in practice, gets rid of a lot of the downsides of the 'free parameters' Thellim is complaining might exist in principle.&nbsp; Nobody's actually going to believe you if you flip a coin six times, get HHHHHT, and claim you decided to flip until you got a tails and then stop.</p>",
      "created_at": "2022-03-29T06:30:41.591+00:00",
      "icon": {
        "id": 248121,
        "keyword": "shadowed earth",
        "url": "https://d1anwqy6ci9o1i.cloudfront.net/users%2F366%2Ficons%2Fzoi28mrzgqc3rb50v1apdm_shadowed+earth.png"
      },
      "updated_at": "2022-03-29T06:30:41.591+00:00",
      "user": {
        "id": 366,
        "username": "Iarwain"
      }
    },
    {
      "id": 1783026,
      "character": {
        "id": 11402,
        "name": "Thellim",
        "screenname": "out-of-equilibrium"
      },
      "character_name": "Thellim",
      "content": "<p>With very very simple statistics, that might, possibly, be true with respect to that exact particular class of disaster that results from 'p-values' lumping different hypotheses and outcomes into weird buckets.&nbsp; There's other disaster classes she'll get to.</p>\r\n<p>But Earth science has been known to ever involve complicated procedures involving dozens of parameters entered into 'stats' computer programs.</p>\r\n<p>Past <em>that </em>point, if the reported-on strength of your evidence isn't independent of the experimenter's private state of mind - and there's no prediction markets, and there's no preregistration of studies including the analysis methods they'll use, and journals accept papers after the evidence gets gathered and analyzed instead of accepting the preregistered paper beforehand, and the journals <em>openly take into account the results when deciding whether to publish the study</em>, meaning experimenters are being <em>openly plied with incentives that are not accuracy incentives</em> - you're kind of screwed.</p>",
      "created_at": "2022-03-29T06:57:17.603+00:00",
      "icon": {
        "id": 192154,
        "keyword": "serious 1",
        "url": "https://d1anwqy6ci9o1i.cloudfront.net/users%2F366%2Ficons%2Fmeuvbswa88mpefrsnr0roo_aimee-garcia-lucifer-3404465.jpg"
      },
      "updated_at": "2022-03-29T06:57:17.603+00:00",
      "user": {
        "id": 366,
        "username": "Iarwain"
      }
    },
    {
      "id": 1783028,
      "character": {
        "id": 13437,
        "name": "Eclipse",
        "screenname": "Earth's-shadow"
      },
      "character_name": "Eclipse",
      "content": "<p>Well, he's definitely not arguing against the point that there ought to be more preregistration of studies, though the idea that&nbsp;<em>journals should accept papers based on their preregistration</em> is one that he hasn't heard before.&nbsp; He likes it in principle, but it's the sort of noble idea that basically never happens in real life.&nbsp; His field is still trying to replace Elsevier journals with open-access ones.</p>",
      "created_at": "2022-03-29T06:58:41.742+00:00",
      "icon": {
        "id": 248121,
        "keyword": "shadowed earth",
        "url": "https://d1anwqy6ci9o1i.cloudfront.net/users%2F366%2Ficons%2Fzoi28mrzgqc3rb50v1apdm_shadowed+earth.png"
      },
      "updated_at": "2022-03-29T06:58:41.742+00:00",
      "user": {
        "id": 366,
        "username": "Iarwain"
      }
    },
    {
      "id": 1783032,
      "character": {
        "id": 11402,
        "name": "Thellim",
        "screenname": "out-of-equilibrium"
      },
      "character_name": "Thellim",
      "content": "<p>Ah, yes.&nbsp; Elsevier.</p>\r\n<p>Earth 'science' is a giant obvious flaming disaster, and you'd think people would be more open to the suggestion that maybe the incredibly complicated private-state-of-mind-dependent statistical analyses would perhaps also be broken and contributing to the giant flaming disaster.</p>",
      "created_at": "2022-03-29T07:00:31.379+00:00",
      "icon": {
        "id": 192155,
        "keyword": "smile",
        "url": "https://d1anwqy6ci9o1i.cloudfront.net/users%2F366%2Ficons%2Fwyv1n0155sdrgkb7svtzcp_aimee-garcia-lucifer-3404491.jpg"
      },
      "updated_at": "2022-03-29T09:09:57.382+00:00",
      "user": {
        "id": 366,
        "username": "Iarwain"
      }
    },
    {
      "id": 1783033,
      "character": {
        "id": 13437,
        "name": "Eclipse",
        "screenname": "Earth's-shadow"
      },
      "character_name": "Eclipse",
      "content": "<p>He really doesn't think that bad stats are the primary problem there -</p>",
      "created_at": "2022-03-29T07:04:36.451+00:00",
      "icon": {
        "id": 248121,
        "keyword": "shadowed earth",
        "url": "https://d1anwqy6ci9o1i.cloudfront.net/users%2F366%2Ficons%2Fzoi28mrzgqc3rb50v1apdm_shadowed+earth.png"
      },
      "updated_at": "2022-03-29T07:04:36.451+00:00",
      "user": {
        "id": 366,
        "username": "Iarwain"
      }
    },
    {
      "id": 1783037,
      "character": {
        "id": 11402,
        "name": "Thellim",
        "screenname": "out-of-equilibrium"
      },
      "character_name": "Thellim",
      "content": "<p>Every single aspect of Earth's science is broken SIMULTANEOUSLY and the stats are PART OF WHAT'S BROKEN.</p>\r\n<p>The 'null hypothesis significance testing' paradigm means that a 10% apparent effect size on a small group and a 3% apparent effect size on a larger group can be treated as a replication having 'reproduced' the original's 'rejection of the null hypothesis' instead of as a <em>failure to reproduce&nbsp;</em>the apparent 10% effect size.</p>\r\n<p>The 'null hypothesis significance testing' paradigm means that journals treat some findings of an experiment as 'failures' to find a 'statistically significant effect' rather than as valid evidence <em>ruling out some possible effect sizes.</em>&nbsp; That journals then don't&nbsp;<em>publish</em> that evidence against larger effect sizes, because they didn't accept on the basis of preregistration, is an enormous blatant filter on the presented evidence <em>which no sane society would tolerate for thirty seconds,</em> and also, a giant blatant incentive that is not an accuracy incentive.&nbsp; If you think in likelihood functions there are no failures or successes, there is no 'significant' or 'insignificant' evidence, there is just the data and the summaries of how likely that data is given different states of the world.</p>\r\n<p>If you've correctly disentangled your hypotheses, likelihood functions from different experiments just stack.&nbsp; You literally just fucking multiply them together to get the combined update.&nbsp; It becomes <em>enormously </em>easier to accumulate evidence across multiple experiments -</p>\r\n<p>- although, yes, anybody who tries this <em>on Earth </em>will no doubt find that their likelihood function ends up zero-everywhere, because different experiments were done under different conditions, <em>as is itself a vastly important fact that needs to be explicitly accounted-for,</em> and which the \"rejection of the null hypothesis\" and \"meta-analysis\" paradigms are&nbsp;<em>overwhelmingly failing in practice</em> to turn up before it's too late.</p>\r\n<p>'Null hypothesis significance testing' rejects the notion of a&nbsp;<em>way reality can be that produces your data.</em>&nbsp; It just says reality isn't like the null hypothesis, now you win, you can publish a paper.&nbsp; That doesn't exactly prompt people to notice if reality is being unlike the null hypothesis in incompatible ways on different occasions.</p>\r\n<p>The 'p-value' paradigm's dependence on the experimenter's private state of mind means that people can't just go out and&nbsp;<em>gather more data,</em> when it turns out they didn't get enough data, because the fact that the experimenter has privately internally chosen how much data to gather breaks the p-value paradigm -</p>",
      "created_at": "2022-03-29T07:14:06.224+00:00",
      "icon": {
        "id": 192507,
        "keyword": "determined",
        "url": "https://d1anwqy6ci9o1i.cloudfront.net/users%2F366%2Ficons%2Fkupnmepgnv82d1vb18ee3_aimee-garcia-lucifer-3404549.jpg"
      },
      "updated_at": "2022-04-02T18:12:11.634+00:00",
      "user": {
        "id": 366,
        "username": "Iarwain"
      }
    },
    {
      "id": 1783038,
      "character": {
        "id": 13437,
        "name": "Eclipse",
        "screenname": "Earth's-shadow"
      },
      "character_name": "Eclipse",
      "content": "<p>Wait, is she saying that people should just be allowed to gather more data any time they feel like it?</p>",
      "created_at": "2022-03-29T07:14:31.892+00:00",
      "icon": {
        "id": 248121,
        "keyword": "shadowed earth",
        "url": "https://d1anwqy6ci9o1i.cloudfront.net/users%2F366%2Ficons%2Fzoi28mrzgqc3rb50v1apdm_shadowed+earth.png"
      },
      "updated_at": "2022-03-29T07:14:31.892+00:00",
      "user": {
        "id": 366,
        "username": "Iarwain"
      }
    },
    {
      "id": 1783040,
      "character": {
        "id": 11402,
        "name": "Thellim",
        "screenname": "out-of-equilibrium"
      },
      "character_name": "Thellim",
      "content": "<p>YES!&nbsp; It's just DATA!&nbsp; It's not going to HURT YOU if you don't MISTREAT it like Earth scientists do!</p>\r\n<p>If the experimentalist's intentions are not telekinetically affecting the data, then your statistical method shouldn't care <em>why</em> they decided to gather the data, the data is telling you about the world and not about the experimenter!&nbsp; People can gather data for any reasons they feel like!&nbsp; Or no reasons at all!&nbsp; Stop telling experimenters how to feel about their data!</p>",
      "created_at": "2022-03-29T07:17:13.251+00:00",
      "icon": {
        "id": 192161,
        "keyword": "incredulous",
        "url": "https://d1anwqy6ci9o1i.cloudfront.net/users%2F366%2Ficons%2F2bzk5g6xzj9l7p0pgbib0p_aimee-garcia-lucifer-3404591.jpg"
      },
      "updated_at": "2022-03-29T07:17:13.251+00:00",
      "user": {
        "id": 366,
        "username": "Iarwain"
      }
    },
    {
      "id": 1783042,
      "character": {
        "id": 13437,
        "name": "Eclipse",
        "screenname": "Earth's-shadow"
      },
      "character_name": "Eclipse",
      "content": "<p>Okay, but then, what stops somebody from just continuing to flip a fair coin until there's a bunch more heads than tails in the results, and then stopping and reporting that the coin is biased towards heads?</p>",
      "created_at": "2022-03-29T07:18:04.115+00:00",
      "icon": {
        "id": 248121,
        "keyword": "shadowed earth",
        "url": "https://d1anwqy6ci9o1i.cloudfront.net/users%2F366%2Ficons%2Fzoi28mrzgqc3rb50v1apdm_shadowed+earth.png"
      },
      "updated_at": "2022-03-29T07:18:04.115+00:00",
      "user": {
        "id": 366,
        "username": "Iarwain"
      }
    },
    {
      "id": 1783044,
      "character": {
        "id": 11402,
        "name": "Thellim",
        "screenname": "out-of-equilibrium"
      },
      "character_name": "Thellim",
      "content": "<p>He is welcome to set up any computer program he likes, in which some coins are biased, some coins are fair, as selected at random according to a known distribution; and an analyst, who knows this prior distribution, is updating her credences correctly using likelihoods; and an experimenter, who does not know the true state of the coin but can observe it, can decide as he pleases when to stop gathering data.</p>\r\n<p>The experimenter will not be able to make the analyst arrive at an ill-calibrated probability distribution.</p>\r\n<p>Now, maybe if the analyst had bad priors, they'd come to bad conclusions.&nbsp; Which is why experimental reports shouldn't report on posteriors like that.&nbsp; But the <em>likelihood functions</em> don't introduce any problems for the analyst, even if the experimenter is deciding how much data to gather based on previous observations; because the experimenter's private decision process does not then <em>affect the likelihood of the additionally gathered data given the true state of the world.</em></p>",
      "created_at": "2022-03-29T07:23:37.747+00:00",
      "icon": {
        "id": 192147,
        "keyword": "grimace smile wide eyes",
        "url": "https://d1anwqy6ci9o1i.cloudfront.net/users%2F366%2Ficons%2F76y95ibxd14a2u1so9rkrt_aimee-garcia-lucifer-3404485.jpg"
      },
      "updated_at": "2022-03-29T07:23:37.747+00:00",
      "user": {
        "id": 366,
        "username": "Iarwain"
      }
    },
    {
      "id": 1783045,
      "character": {
        "id": 13437,
        "name": "Eclipse",
        "screenname": "Earth's-shadow"
      },
      "character_name": "Eclipse",
      "content": "<p>...he doesn't see how that prevents, in practice, the experimenter from continuing to flip a fair coin until it shows an excess of heads.</p>",
      "created_at": "2022-03-29T07:24:22.868+00:00",
      "icon": {
        "id": 248121,
        "keyword": "shadowed earth",
        "url": "https://d1anwqy6ci9o1i.cloudfront.net/users%2F366%2Ficons%2Fzoi28mrzgqc3rb50v1apdm_shadowed+earth.png"
      },
      "updated_at": "2022-03-29T07:24:22.868+00:00",
      "user": {
        "id": 366,
        "username": "Iarwain"
      }
    },
    {
      "id": 1783048,
      "character": {
        "id": 11402,
        "name": "Thellim",
        "screenname": "out-of-equilibrium"
      },
      "character_name": "Thellim",
      "content": "<p>He might perhaps find it illuminating to write some computer simulations along these lines, until he has been convinced of the point that you cannot, in fact, convince a lawful reasoner of anything you want, by deciding when to gather more data.</p>\r\n<p>After all:&nbsp; If that were possible, a lawful reasoner could plan to convince <em>themselves</em> of a fair coin being biased heads, by deciding themselves to keep flipping until it showed an excess of heads.&nbsp; And then they would know in advance which direction they would update later, as is obviously mathematically impossible.</p>",
      "created_at": "2022-03-29T07:28:36.040+00:00",
      "icon": {
        "id": 192154,
        "keyword": "serious 1",
        "url": "https://d1anwqy6ci9o1i.cloudfront.net/users%2F366%2Ficons%2Fmeuvbswa88mpefrsnr0roo_aimee-garcia-lucifer-3404465.jpg"
      },
      "updated_at": "2022-03-29T07:30:45.796+00:00",
      "user": {
        "id": 366,
        "username": "Iarwain"
      }
    },
    {
      "id": 1783049,
      "character": {
        "id": 13437,
        "name": "Eclipse",
        "screenname": "Earth's-shadow"
      },
      "character_name": "Eclipse",
      "content": "<p>Huh?</p>",
      "created_at": "2022-03-29T07:28:43.115+00:00",
      "icon": {
        "id": 248121,
        "keyword": "shadowed earth",
        "url": "https://d1anwqy6ci9o1i.cloudfront.net/users%2F366%2Ficons%2Fzoi28mrzgqc3rb50v1apdm_shadowed+earth.png"
      },
      "updated_at": "2022-03-29T07:28:43.115+00:00",
      "user": {
        "id": 366,
        "username": "Iarwain"
      }
    },
    {
      "id": 1783051,
      "character": {
        "id": 11402,
        "name": "Thellim",
        "screenname": "out-of-equilibrium"
      },
      "character_name": "Thellim",
      "content": "<p>It's magic math.&nbsp; Earthlings will never be able to understand it.&nbsp; It comes from another world and has inscrutable mystical properties like \"If you start out thinking it's 70% probable that some coin is fair, nothing you can possibly plan to do by gathering more data, analyzing it a particular way, etcetera etcetera, can result in you expecting for that analysis to make you believe on average that the coin is not 70% probably fair.\"&nbsp; All of the sinister misdeeds that 'p-values' are trying to prevent by, for example, not letting naughty experimenters gather more data whenever they feel like it, are just flatly mathematically impossible in the first place under this system.</p>\r\n<p>What she's hoping at this point is that she can get a system set up where some Earthlings are using the magic math, even though it seems very 'subjective' and that makes for weird internal feelings that make them want to reject it, paying Earthlings enough to do it <em>anyways,</em> just, just <em>trying it to see if it works,</em> and maybe leads into less massive replication failures, and then they get interesting results that other people want to pay for, and the system can continue under its own momentum.&nbsp; And prediction markets; and professional replicators; and impact markets instead of journal citation counts, for important results that really do reproduce, to establish purer accuracy incentives; and specialized analysts and specialized writers; and everything else the system needs to fix everything broken about it simultaneously, <em>in one small part of it somewhere.</em></p>\r\n<p><br />Thellim has three months left, on one of her dominant hypotheses about how this world works, before she suddenly starts thinking that likelihood functions are 'subjective' and meaningless and icky.&nbsp; She has to build something that will sustain itself before then.</p>",
      "created_at": "2022-03-29T07:38:57.691+00:00",
      "icon": {
        "id": 192508,
        "keyword": "looking up",
        "url": "https://d1anwqy6ci9o1i.cloudfront.net/users%2F366%2Ficons%2Fnjn216klk3pyjiirl2qm1m_aimee-garcia-lucifer-3404546.jpg"
      },
      "updated_at": "2022-03-29T08:08:44.010+00:00",
      "user": {
        "id": 366,
        "username": "Iarwain"
      }
    },
    {
      "id": 1783052,
      "character": {
        "id": 13437,
        "name": "Eclipse",
        "screenname": "Earth's-shadow"
      },
      "character_name": "Eclipse",
      "content": "<p>Yeah, nothing's getting built in three months, he's pretty sure.</p>",
      "created_at": "2022-03-29T07:39:12.074+00:00",
      "icon": {
        "id": 248121,
        "keyword": "shadowed earth",
        "url": "https://d1anwqy6ci9o1i.cloudfront.net/users%2F366%2Ficons%2Fzoi28mrzgqc3rb50v1apdm_shadowed+earth.png"
      },
      "updated_at": "2022-03-29T07:39:12.074+00:00",
      "user": {
        "id": 366,
        "username": "Iarwain"
      }
    },
    {
      "id": 1783054,
      "character": {
        "id": 11402,
        "name": "Thellim",
        "screenname": "out-of-equilibrium"
      },
      "character_name": "Thellim",
      "content": "<p>Why not?&nbsp; <em>Why?</em>&nbsp; Three months is so much time!&nbsp; It's 90 days!&nbsp; People can do a lot in 90 days!&nbsp; They just all have to make the correct moves simultaneously!&nbsp; It's&nbsp;<em>not that hard to coordinate!</em>&nbsp; They just have to look inside them for whatever makes them feel icky about the thought of coordinating and&nbsp;<em>ignore that icky feeling,</em> just once, just this one time, and they can maybe set up a fragment of real Civilization that would - that would, even if something happens to Thellim, be able to figure things out, put her back, eventually, to the way that she was -</p>",
      "created_at": "2022-03-29T07:42:42.751+00:00",
      "icon": {
        "id": 192116,
        "keyword": "scared",
        "url": "https://d1anwqy6ci9o1i.cloudfront.net/users%2F366%2Ficons%2F6wlhaagr457xg759z7lej_aimee-garcia-lucifer-3404457.jpg"
      },
      "updated_at": "2022-03-29T07:42:42.751+00:00",
      "user": {
        "id": 366,
        "username": "Iarwain"
      }
    },
    {
      "id": 1783055,
      "character": {
        "id": 13437,
        "name": "Eclipse",
        "screenname": "Earth's-shadow"
      },
      "character_name": "Eclipse",
      "content": "<p>He has to go.</p>",
      "created_at": "2022-03-29T07:43:11.924+00:00",
      "icon": {
        "id": 248121,
        "keyword": "shadowed earth",
        "url": "https://d1anwqy6ci9o1i.cloudfront.net/users%2F366%2Ficons%2Fzoi28mrzgqc3rb50v1apdm_shadowed+earth.png"
      },
      "updated_at": "2022-03-29T07:43:11.924+00:00",
      "user": {
        "id": 366,
        "username": "Iarwain"
      }
    },
    {
      "id": 1783056,
      "character": {
        "id": 11402,
        "name": "Thellim",
        "screenname": "out-of-equilibrium"
      },
      "character_name": "Thellim",
      "content": "",
      "created_at": "2022-03-29T07:43:34.943+00:00",
      "icon": {
        "id": 192505,
        "keyword": "folded",
        "url": "https://d1anwqy6ci9o1i.cloudfront.net/users%2F366%2Ficons%2Fcdnhmzqn0mj0wmhyviux36a_aimee-garcia-lucifer-3404382.jpg"
      },
      "updated_at": "2022-03-29T07:43:34.943+00:00",
      "user": {
        "id": 366,
        "username": "Iarwain"
      }
    },
    {
      "id": 1783060,
      "character": {
        "id": 11402,
        "name": "Thellim",
        "screenname": "out-of-equilibrium"
      },
      "character_name": "Thellim",
      "content": "<p>Thellim is aware that Earth is not literally pessimal.&nbsp; But sometimes it's hard to see how her situation could realistically be worse, anthropically speaking, assuming it's a requirement that she landed in a populated world instead of somewhere in intergalactic space.&nbsp; It feels like this planetary setup is about as bad as a planetary setup could get without stuff <em>actually </em>collapsing.</p>\r\n<p>...why couldn't she have just ended up in a regular fantasy universe, one where she'd have her own economicmagic already, and without her mind having been warped in the process? &nbsp;Someplace that would actually listen to her, and let her improve it.</p>\r\n<p>Maybe with a harem. &nbsp;A harem of magical boyfriends would be nice.</p>\r\n<p>She hopes the other dath ilani on the airplane ended up in better places.</p>\r\n<p>Somebody has to be worst-off, after all.&nbsp; With any luck, that was her, and the other dath ilani are in happier, less fraught, less dangerous situations than this.</p>",
      "created_at": "2022-03-29T08:00:44.343+00:00",
      "icon": {
        "id": 193421,
        "keyword": "entering",
        "url": "https://d1anwqy6ci9o1i.cloudfront.net/users%2F366%2Ficons%2F0n0tq4z0c69phgly58hvr_aimee-garcia-lucifer-3404552.jpg"
      },
      "updated_at": "2022-03-29T09:29:33.859+00:00",
      "user": {
        "id": 366,
        "username": "Iarwain"
      }
    },
    {
      "id": 1784212,
      "character": null,
      "character_name": null,
      "content": "<p>(<a href=\"/replies/1777291#reply-1777291\"><strong>Return to the main Planecrash continuity</strong></a>.)</p>",
      "created_at": "2022-03-31T02:46:08.962+00:00",
      "icon": null,
      "updated_at": "2022-03-31T02:46:08.962+00:00",
      "user": {
        "id": 366,
        "username": "Iarwain"
      }
    }
  ]
}